{
	"menu":{
		"1001":{
			"name":"TV直播 水果生鲜",
			"url":"http://www/jd.com",
			"children":{
				"100101":{
					"name":"最新上架",
					"url":"http://www/jd.com",
					"children":{
						"10010101":{
							"name":"百香果",
							"url":"http://www/jd.com"
						},
						"10010102":{
							"name":"柑橘类",
							"url":"http://www/jd.com"
						},
						"10010103":{
							"name":"瓜类",
							"url":"http://www/jd.com"
						},
						"10010104":{
							"name":"火龙果",
							"url":"http://www/jd.com"
						},
						"10010105":{
							"name":"梨",
							"url":"http://www/jd.com"
						},
						"10010106":{
							"name":"芒果",
							"url":"http://www/jd.com"
						}
					}
				},
				"100102":{
					"name":"热销排行",
					"url":"http://www/jd.com",
					"children":{
						"10010101":{
							"name":"苹果",
							"url":"http://www/jd.com"
						},
						"10010102":{
							"name":"葡萄/提子",
							"url":"http://www/jd.com"
						},
						"10010103":{
							"name":"热带水果",
							"url":"http://www/jd.com"
						},
						"10010104":{
							"name":"人参果",
							"url":"http://www/jd.com"
						},
						"10010105":{
							"name":"桃/李/杏",
							"url":"http://www/jd.com"
						},
						"10010106":{
							"name":"西梅",
							"url":"http://www/jd.com"
						}
					}
				}
			}
		},
		"1002":{
			"name":"护肤 美妆",
			"url":"http://www.jd.com",
			"children":{
				"100201":{
					"name":"面部护理",
					"url":"http://www/jd.com",
					"children":{
						"10020101":{
							"name":"洁面乳",
							"url":"http://www/jd.com"
						},
						"10020102":{
							"name":"爽肤水",
							"url":"http://www/jd.com"
						},
						"10020103":{
							"name":"精华露",
							"url":"http://www/jd.com"
						},
						"10020104":{
							"name":"乳液/面霜",
							"url":"http://www/jd.com"
						},
						"10020105":{
							"name":"眼部护理",
							"url":"http://www/jd.com"
						},
						"10020106":{
							"name":"男士专区",
							"url":"http://www/jd.com"
						}
					}
				},
				"100202":{
					"name":"全身护理",
					"url":"http://www/jd.com",
					"children":{
						"10020201":{
							"name":"洗发护发",
							"url":"http://www/jd.com"
						},
						"10020202":{
							"name":"染发造型",
							"url":"http://www/jd.com"
						},
						"10020203":{
							"name":"沐浴",
							"url":"http://www/jd.com"
						},
						"10020204":{
							"name":"洗护套餐",
							"url":"http://www/jd.com"
						},
						"10020205":{
							"name":"脱毛",
							"url":"http://www/jd.com"
						},
						"10020206":{
							"name":"身体乳",
							"url":"http://www/jd.com"
						}
					}
				},
				"100203":{
					"name":"女性护理",
					"url":"http://www/jd.com",
					"children":{
						"10020301":{
							"name":"洗液",
							"url":"http://www/jd.com"
						},
						"10020302":{
							"name":"面膜",
							"url":"http://www/jd.com"
						},
						"10020303":{
							"name":"香水",
							"url":"http://www/jd.com"
						},
					}
				},
				"100204":{
					"name":"美容工具",
					"url":"http://www/jd.com",
					"children":{
						"10020401":{
							"name":"剃须刀",
							"url":"http://www/jd.com"
						},
						"10020402":{
							"name":"脱毛器",
							"url":"http://www/jd.com"
						},
						"10020403":{
							"name":"掏耳器",
							"url":"http://www/jd.com"
						},
						"10020404":{
							"name":"湿巾",
							"url":"http://www/jd.com"
						},
					}
				},
				"100205":{
					"name":"化妆用品",
					"url":"http://www/jd.com",
					"children":{
						"10020501":{
							"name":"防晒隔离",
							"url":"http://www/jd.com"
						},
						"10020502":{
							"name":"BB霜",
							"url":"http://www/jd.com"
						},
						"10020503":{
							"name":"彩妆套餐",
							"url":"http://www/jd.com"
						},
						"10020504":{
							"name":"美容美发",
							"url":"http://www/jd.com"
						},
						"10020505":{
							"name":"卸妆用品",
							"url":"http://www/jd.com"
						},
						"10020506":{
							"name":"睫毛膏",
							"url":"http://www/jd.com"
						},
						"10020507":{
							"name":"粉底散粉",
							"url":"http://www/jd.com"
						}
					}
				}
			}
		},
		"1003":{
			"name":"服装 鞋包",
			"url":"http://www.jd.com",
			"children":{
				"100301":{
					"name":"内衣",
					"url":"http://www/jd.com",
					"children":{
						"10030101":{
							"name":"文胸",
							"url":"http://www/jd.com"
						},
						"10030102":{
							"name":"塑身",
							"url":"http://www/jd.com"
						},
						"10030103":{
							"name":"睡衣",
							"url":"http://www/jd.com"
						},
						"10030104":{
							"name":"家居服",
							"url":"http://www/jd.com"
						},
						"10030105":{
							"name":"套装",
							"url":"http://www/jd.com"
						},
						"10030106":{
							"name":"内裤",
							"url":"http://www/jd.com"
						}
					}
				},
				"100302":{
					"name":"女装",
					"url":"http://www/jd.com",
					"children":{
						"10030201":{
							"name":"衬衫",
							"url":"http://www/jd.com"
						},
						"10030202":{
							"name":"T恤",
							"url":"http://www/jd.com"
						},
						"10030203":{
							"name":"针织",
							"url":"http://www/jd.com"
						},
						"10030204":{
							"name":"外套",
							"url":"http://www/jd.com"
						},
						"10030205":{
							"name":"羽绒服",
							"url":"http://www/jd.com"
						},
						"10030206":{
							"name":"裙子",
							"url":"http://www/jd.com"
						}
					}
				},
				"100303":{
					"name":"男装",
					"url":"http://www/jd.com",
					"children":{
						"10030301":{
							"name":"衬衫",
							"url":"http://www/jd.com"
						},
						"10030302":{
							"name":"T恤",
							"url":"http://www/jd.com"
						},
						"10030303":{
							"name":"针织",
							"url":"http://www/jd.com"
						},
						"10030304":{
							"name":"外套",
							"url":"http://www/jd.com"
						},
						"10030305":{
							"name":"羽绒服",
							"url":"http://www/jd.com"
						},
					}
				},
				"100304":{
					"name":"配饰",
					"url":"http://www/jd.com",
					"children":{
						"10030401":{
							"name":"眼镜",
							"url":"http://www/jd.com"
						},
						"10030402":{
							"name":"围巾",
							"url":"http://www/jd.com"
						},
						"10030403":{
							"name":"依照配饰",
							"url":"http://www/jd.com"
						},
						"10030404":{
							"name":"皮带",
							"url":"http://www/jd.com"
						},
					}
				},
				"100305":{
					"name":"男鞋",
					"url":"http://www/jd.com",
					"children":{
						"10030501":{
							"name":"皮鞋",
							"url":"http://www/jd.com"
						},
						"10030502":{
							"name":"休闲鞋",
							"url":"http://www/jd.com"
						},
						"10030503":{
							"name":"凉鞋/沙滩鞋",
							"url":"http://www/jd.com"
						}
					}
				},
				"100306":{
					"name":"女鞋",
					"url":"http://www/jd.com",
					"children":{
						"10030601":{
							"name":"单鞋",
							"url":"http://www/jd.com"
						},
						"10030602":{
							"name":"休闲鞋",
							"url":"http://www/jd.com"
						},
						"10030603":{
							"name":"靴子",
							"url":"http://www/jd.com"
						}
					}
				}
			}
		},
		"1004":{
			"name":"家居 日用",
			"url":"http://www.jd.com",
			"children":{
				"100401":{
					"name":"家纺",
					"url":"http://www/jd.com",
					"children":{
						"10040101":{
							"name":"床品件套",
							"url":"http://www/jd.com"
						},
						"10040102":{
							"name":"被子/枕芯",
							"url":"http://www/jd.com"
						},
						"10040103":{
							"name":"凉席",
							"url":"http://www/jd.com"
						},
						"10040104":{
							"name":"电热毯",
							"url":"http://www/jd.com"
						}
					}
				},
				"100402":{
					"name":"生活日用",
					"url":"http://www/jd.com",
					"children":{
						"10040201":{
							"name":"晒衣架",
							"url":"http://www/jd.com"
						},
						"10040202":{
							"name":"收纳用品",
							"url":"http://www/jd.com"
						},
						"10040203":{
							"name":"清洁用品",
							"url":"http://www/jd.com"
						},
						"10040204":{
							"name":"安全套",
							"url":"http://www/jd.com"
						},
						"10040205":{
							"name":"雨伞",
							"url":"http://www/jd.com"
						},
						"10040206":{
							"name":"杯子",
							"url":"http://www/jd.com"
						}
					}
				},
				"100403":{
					"name":"厨房日用",
					"url":"http://www/jd.com",
					"children":{
						"10040301":{
							"name":"锅具",
							"url":"http://www/jd.com"
						},
						"10040302":{
							"name":"餐具",
							"url":"http://www/jd.com"
						},
						"10040303":{
							"name":"刀具",
							"url":"http://www/jd.com"
						},
					}
				},
				"100404":{
					"name":"家居生活",
					"url":"http://www/jd.com",
					"children":{
						"10040401":{
							"name":"礼品",
							"url":"http://www/jd.com"
						},
						"10040402":{
							"name":"麻将机",
							"url":"http://www/jd.com"
						},
						"10040403":{
							"name":"空气床",
							"url":"http://www/jd.com"
						},
						"10040404":{
							"name":"母婴用品",
							"url":"http://www/jd.com"
						},
					}
				}
			}
		},
		"1005":{
			"name":"家电 数码",
			"url":"http://www.jd.com",
			"children":{
				"100501":{
					"name":"电脑整机",
					"url":"http://www/jd.com",
					"children":{
						"10050101":{
							"name":"台式",
							"url":"http://www/jd.com"
						},
						"10050102":{
							"name":"笔记本",
							"url":"http://www/jd.com"
						},
						"10050103":{
							"name":"平板电脑",
							"url":"http://www/jd.com"
						}
					}
				},
				"100502":{
					"name":"数码摄像",
					"url":"http://www/jd.com",
					"children":{
						"10050201":{
							"name":"数码相机",
							"url":"http://www/jd.com"
						},
						"10050202":{
							"name":"单反相机",
							"url":"http://www/jd.com"
						},
						"10050203":{
							"name":"数码摄像机",
							"url":"http://www/jd.com"
						},
						"10050204":{
							"name":"导航仪",
							"url":"http://www/jd.com"
						}
					}
				},
				"100503":{
					"name":"家电",
					"url":"http://www/jd.com",
					"children":{
						"10050301":{
							"name":"空调",
							"url":"http://www/jd.com"
						},
						"10050302":{
							"name":"平板电视",
							"url":"http://www/jd.com"
						},
						"10050303":{
							"name":"冰箱",
							"url":"http://www/jd.com"
						},
						"10050304":{
							"name":"洗衣机",
							"url":"http://www/jd.com"
						},
						"10050305":{
							"name":"烟机/灶具",
							"url":"http://www/jd.com"
						}
					}
				},
				"100504":{
					"name":"家具电器",
					"url":"http://www/jd.com",
					"children":{
						"10050401":{
							"name":"取暖器",
							"url":"http://www/jd.com"
						},
						"10050402":{
							"name":"电风扇",
							"url":"http://www/jd.com"
						},
						"10050403":{
							"name":"吸尘器",
							"url":"http://www/jd.com"
						},
						"10050404":{
							"name":"挂烫机",
							"url":"http://www/jd.com"
						},
						"10050405":{
							"name":"干衣机",
							"url":"http://www/jd.com"
						},
						"10050406":{
							"name":"吹风机",
							"url":"http://www/jd.com"
						},
						"10050407":{
							"name":"饮水机",
							"url":"http://www/jd.com"
						}
					}
				},
				"100505":{
					"name":"厨房电器",
					"url":"http://www/jd.com",
					"children":{
						"10050501":{
							"name":"豆浆机",
							"url":"http://www/jd.com"
						},
						"10050502":{
							"name":"电饭煲",
							"url":"http://www/jd.com"
						},
						"10050503":{
							"name":"电压力锅",
							"url":"http://www/jd.com"
						},
						"10050504":{
							"name":"微波炉",
							"url":"http://www/jd.com"
						},
						"10050505":{
							"name":"电磁炉",
							"url":"http://www/jd.com"
						},
						"10050506":{
							"name":"电水壶",
							"url":"http://www/jd.com"
						},
						"10050507":{
							"name":"电热锅",
							"url":"http://www/jd.com"
						}
					}
				},
				"100506":{
					"name":"五金电器",
					"url":"http://www/jd.com",
					"children":{
						"10050601":{
							"name":"水槽",
							"url":"http://www/jd.com"
						},
						"10050602":{
							"name":"水龙头",
							"url":"http://www/jd.com"
						},
						"10050603":{
							"name":"灯具",
							"url":"http://www/jd.com"
						}
					}
				}
			}
		},
		"1006":{
			"name":"酒水 保健",
			"url":"http://www.jd.com",
			"children":{
				"100601":{
					"name":"健身器材",
					"url":"http://www/jd.com",
					"children":{
						"10060101":{
							"name":"跑步机",
							"url":"http://www/jd.com"
						},
						"10060102":{
							"name":"按摩器材",
							"url":"http://www/jd.com"
						},
						"10060103":{
							"name":"健身机",
							"url":"http://www/jd.com"
						}
					}
				},
				"100602":{
					"name":"营养保健",
					"url":"http://www/jd.com",
					"children":{
						"10060201":{
							"name":"保健品",
							"url":"http://www/jd.com"
						},
						"10060202":{
							"name":"干果/零食",
							"url":"http://www/jd.com"
						},
						"10060203":{
							"name":"酒水",
							"url":"http://www/jd.com"
						}
					}
				},
				"100603":{
					"name":"婴童用品",
					"url":"http://www/jd.com",
					"children":{
						"10060301":{
							"name":"奶粉",
							"url":"http://www/jd.com"
						},
						"10060302":{
							"name":"寝具服饰",
							"url":"http://www/jd.com"
						},
						"10060303":{
							"name":"寝具服饰",
							"url":"http://www/jd.com"
						},
						"10060304":{
							"name":"喂哺用品",
							"url":"http://www/jd.com"
						},
						"10060305":{
							"name":"玩具乐器",
							"url":"http://www/jd.com"
						},
						"10060306":{
							"name":"妈妈专区",
							"url":"http://www/jd.com"
						}
					}
				},
				"100604":{
					"name":"旅游",
					"url":"http://www/jd.com",
					"children":{
						"10060401":{
							"name":"国内游",
							"url":"http://www/jd.com"
						},
						"10060402":{
							"name":"国外游",
							"url":"http://www/jd.com"
						}
					}
				}
			}
		},
		"1007":{
			"name":"饰品 礼品",
			"url":"http://www.jd.com",
			"children":{
				"100701":{
					"name":"项链吊坠",
					"url":"http://www/jd.com",
					"children":{
						"10070101":{
							"name":"心形",
							"url":"http://www/jd.com"
						},
						"10070102":{
							"name":"月牙坠",
							"url":"http://www/jd.com"
						},
						"10060103":{
							"name":"一心一意",
							"url":"http://www/jd.com"
						}
					}
				},
				"100702":{
					"name":"手链手镯",
					"url":"http://www/jd.com",
					"children":{
						"10070201":{
							"name":"银饰",
							"url":"http://www/jd.com"
						},
						"10060202":{
							"name":"金饰",
							"url":"http://www/jd.com"
						}
					}
				},
				"100703":{
					"name":"戒指",
					"url":"http://www/jd.com",
					"children":{
						"10070301":{
							"name":"情人",
							"url":"http://www/jd.com"
						},
						"10070302":{
							"name":"表白",
							"url":"http://www/jd.com"
						},
						"10070303":{
							"name":"求婚",
							"url":"http://www/jd.com"
						},
						"10070304":{
							"name":"金婚",
							"url":"http://www/jd.com"
						},
						"10070305":{
							"name":"银婚",
							"url":"http://www/jd.com"
						}
					}
				},
				"100704":{
					"name":"耳环",
					"url":"http://www/jd.com",
					"children":{
						"10060401":{
							"name":"送女友",
							"url":"http://www/jd.com"
						},
						"10060402":{
							"name":"送爱人",
							"url":"http://www/jd.com"
						}
					}
				}
			}
		}
	},
	"Tpicture":{
		"1-1001":{
			"time":"[19:30-20:13]",
			"_img":"../images/14646642752106207338.jpg",
			"live":"../images/miaosha.png",
			"desc":"花花公子夏季商务男鞋必备组",
			"money":"￥199.00"
		},
		"1-1002":{
			"time":"[23:17-23:59]",
			"_img":"../images/5715e7832574e.jpg",
			"live":"../images/miaosha.png",
			"desc":"艾力士汽车养护安全套组",
			"money":"￥299.00"
		},
		"1-1003":{
			"time":"[01:32-02:15]",
			"_img":"../images/14679608771500773372.jpg",
			"live":"../images/miaosha.png",
			"desc":"诗蘭庭寝具4+4+4特惠组",
			"money":"￥339.00"
		},
		"1-1004":{
			"time":"[02:17-03:02]",
			"_img":"../images/57875942c42c5.jpg",
			"live":"../images/miaosha.png",
			"desc":"迪格尔斯精致男士爆款POLO衫2+2超值组",
			"money":"￥199.00"
		},
		"1-1005":{
			"time":"[19:30-20:13]",
			"_img":"../images/572345874760b.jpg",
			"live":"../images/miaosha.png",
			"desc":"浪莎欧美时尚修身凉感哈伦裤8+10超值组",
			"money":"￥199.00"
		},
		"1-1006":{
			"time":"[23:17-23:59]",
			"_img":"../images/14712472631725579189.jpg",
			"live":"../images/miaosha.png",
			"desc":"馨之屋水精灵+洗衣机尊享组",
			"money":"￥299.00"
		},
		"1-1007":{
			"time":"[01:32-02:15]",
			"_img":"../images/14695065041807514364.jpg",
			"live":"../images/miaosha.png",
			"desc":"迪菲怡时尚花朵烫钻网纱衫4件超值组",
			"money":"￥339.00"
		},
		"1-1008":{
			"time":"[02:17-03:02]",
			"_img":"../images/1462511452874472747.jpg",
			"live":"../images/miaosha.png",
			"desc":"家洁灵多功能收纳箱4+10套组",
			"money":"￥199.00"
		},
		"1-1009":{
			"time":"[07:30-09:13]",
			"_img":"../images/575fb9f73b4c6.jpg",
			"live":"../images/miaosha.png",
			"desc":"浪莎完美夏日时尚印花蝙蝠衫5+4超值组",
			"money":"￥199.00"
		},
		"1-1010":{
			"time":"[09:17-13:59]",
			"_img":"../images/5770a07b5c9fe.jpg",
			"live":"../images/miaosha.png",
			"desc":"20L禧又多土榨纯香菜籽油超值秒杀组",
			"money":"￥299.00"
		},
		"1-1011":{
			"time":"[13:32-01:15]",
			"_img":"../images/14679661151451704094.jpg",
			"live":"../images/miaosha.png",
			"desc":"U.S.POLOASSN.绅士亚麻休闲舒适长裤",
			"money":"￥339.00"
		},
		"1-1012":{
			"time":"[02:17-03:02]",
			"_img":"../images/s1_28823.jpg",
			"live":"../images/miaosha.png",
			"desc":"台湾胡子王钛金刀1+1劲爆组",
			"money":"￥199.00"
		}
	},
	"Ypicture":{
		"2-1001":{
			"time":"[07:30-09:13]",
			"_img":"../images/575fb9f73b4c6.jpg",
			"live":"../images/miaosha.png",
			"desc":"浪莎完美夏日时尚印花蝙蝠衫5+4超值组",
			"money":"￥199.00"
		},
		"2-1002":{
			"time":"[09:17-13:59]",
			"_img":"../images/5770a07b5c9fe.jpg",
			"live":"../images/miaosha.png",
			"desc":"20L禧又多土榨纯香菜籽油超值秒杀组",
			"money":"￥299.00"
		},
		"2-1003":{
			"time":"[13:32-01:15]",
			"_img":"../images/14679661151451704094.jpg",
			"live":"../images/miaosha.png",
			"desc":"U.S.POLOASSN.绅士亚麻休闲舒适长裤",
			"money":"￥339.00"
		},
		"2-1004":{
			"time":"[02:17-03:02]",
			"_img":"../images/s1_28823.jpg",
			"live":"../images/miaosha.png",
			"desc":"台湾胡子王钛金刀1+1劲爆组",
			"money":"￥199.00"
		},
		"2-1005":{
			"time":"[19:30-20:13]",
			"_img":"../images/572345874760b.jpg",
			"live":"../images/miaosha.png",
			"desc":"浪莎欧美时尚修身凉感哈伦裤8+10超值组",
			"money":"￥199.00"
		},
		"2-1006":{
			"time":"[23:17-23:59]",
			"_img":"../images/14712472631725579189.jpg",
			"live":"../images/miaosha.png",
			"desc":"馨之屋水精灵+洗衣机尊享组",
			"money":"￥299.00"
		},
		"2-1007":{
			"time":"[01:32-02:15]",
			"_img":"../images/14695065041807514364.jpg",
			"live":"../images/miaosha.png",
			"desc":"迪菲怡时尚花朵烫钻网纱衫4件超值组",
			"money":"￥339.00"
		},
		"2-1008":{
			"time":"[02:17-03:02]",
			"_img":"../images/1462511452874472747.jpg",
			"live":"../images/miaosha.png",
			"desc":"家洁灵多功能收纳箱4+10套组",
			"money":"￥199.00"
		}
	},
	"recommend":{
		"1001":{
			"_img":"../images/1466761066497611605.jpg",
			"url":"#",
			"desc":"浪莎完美夏日时尚印花蝙蝠衫5+4超值组",
			"money":"￥199.00",
			"buy":"购买",
			"rexiao":"已热销：46件"
		},
		"1002":{
			"_img":"../images/5746705c9f7a7.jpg",
			"url":"#",
			"desc":"浪莎完美夏日时尚印花蝙蝠衫5+4超值组",
			"money":"￥99.00",
			"buy":"购买",
			"rexiao":"已热销：1719件"
		},
		"1003":{
			"_img":"../images/1458814627218654138.jpg",
			"url":"#",
			"desc":"浪莎完美夏日时尚印花蝙蝠衫5+4超值组",
			"money":"￥199.00",
			"buy":"购买",
			"rexiao":"已热销：230件"
		},
		"1004":{
			"_img":"../images/s1_28823.jpg",
			"url":"#",
			"desc":"浪莎完美夏日时尚印花蝙蝠衫5+4超值组",
			"money":"￥199.00",
			"buy":"购买",
			"rexiao":"已热销：53232件"
		}
	},
	"Cleft":{
		"list":{
			"1001":{
				"name":"连衣裙",
				"url":"#"
			},
			"1002":{
				"name":"内衣",
				"url":"#"
			},
			"1003":{
				"name":"男式衬衫",
				"url":"#"
			},
			"1004":{
				"name":"男士T恤",
				"url":"#"
			},
			"1005":{
				"name":"男裤",
				"url":"#"
			},
			"1006":{
				"name":"时尚女包",
				"url":"#"
			},
			"1007":{
				"name":"男鞋",
				"url":"#"
			},
			"1008":{
				"name":"手表",
				"url":"#"
			},
			"1009":{
				"name":"手链手镯",
				"url":"#"
			}
		},
		"pic1":{
			"1001":{
				"_img":"../images/57a7fd30a4dcd.jpg",
				"url":"#"
			}
		},
		"pic2":{
			"1001":{
				"_img":"../images/57baaaa43b84f.jpg",
				"url":"#"
			}
		}	
	},
	"Cright":{
		"2001":{
			"_img":"../images/1470035469419022993.jpg",
			"url":"#",
			"desc":"迪菲怡时尚花朵烫钻网纱衫4件超值组",
			"money":"￥168",
			"buy":"购买"
		},
		"2002":{
			"_img":"../images/1467966115730948033.jpg",
			"url":"#",
			"desc":"迪菲怡时尚花朵烫钻网纱衫4件超值组",
			"money":"￥299",
			"buy":"购买"
		},
		"2003":{
			"_img":"../images/1467967340692026455.jpg",
			"url":"#",
			"desc":"迪菲怡时尚花朵烫钻网纱衫4件超值组",
			"money":"￥169",
			"buy":"购买"
		},
		"2004":{
			"_img":"../images/1469506504175461855.jpg",
			"url":"deail.html",
			"desc":"迪菲怡时尚花朵烫钻网纱衫4件超值组",
			"money":"￥298",
			"buy":"购买"
		},
		"2005":{
			"_img":"../images/14657843461118271439.jpg",
			"url":"#",
			"desc":"迪菲怡时尚花朵烫钻网纱衫4件超值组",
			"money":"￥168",
			"buy":"购买"
		},
		"2006":{
			"_img":"../images/14643449001289719327.jpg",
			"url":"#",
			"desc":"试尔雅大牌风范碎花飘逸长裙",
			"money":"￥168",
			"buy":"购买"
		}
	},
	"Bleft":{
		"list":{
			"1001":{
				"name":"面膜",
				"url":"#"
			},
			"1002":{
				"name":"染发造型",
				"url":"#"
			},
			"1003":{
				"name":"BB霜",
				"url":"#"
			},
			"1004":{
				"name":"香水",
				"url":"#"
			},
			"1005":{
				"name":"皂",
				"url":"#"
			},
			"1006":{
				"name":"乳液面霜",
				"url":"#"
			},
			"1007":{
				"name":"眼部护理",
				"url":"#"
			}
		},
		"pic1":{
			"1001":{
				"_img":"../images/57baad615dbb9.jpg",
				"url":"#"
			}
		},
		"pic2":{
			"1001":{
				"_img":"../images/5795c96e8c695.jpg",
				"url":"#"
			}
		}	
	},
	"Bright":{
		"3001":{
			"_img":"../images/1461896722744288251.jpg",
			"url":"#",
			"desc":"一叶子蜂王浆4D提拉面膜尊享组",
			"money":"￥168",
			"buy":"购买"
		},
		"3002":{
			"_img":"../images/1463643399862159457.jpg",
			"url":"#",
			"desc":"冰希黎boitown浪漫香氛情人节",
			"money":"￥299",
			"buy":"购买"
		},
		"3003":{
			"_img":"../images/1462501232189165251.jpg",
			"url":"#",
			"desc":"（购销）藤井焗油染发膏超值2+6升级组",
			"money":"￥169",
			"buy":"购买"
		},
		"3004":{
			"_img":"../images/s1_32930.jpg",
			"url":"#",
			"desc":"朗圣洁生物活性固齿修复牙膏升级组",
			"money":"￥298",
			"buy":"购买"
		},
		"3005":{
			"_img":"../images/1456469325967050708.jpg",
			"url":"#",
			"desc":"英国Morgan's马奶紧致无痕超值组",
			"money":"￥168",
			"buy":"购买"
		},
		"3006":{
			"_img":"../images/s1_31516.jpg",
			"url":"#",
			"desc":"（特卖）韩束红动中国十效裸妆修容霜套组",
			"money":"￥168",
			"buy":"购买"
		}
	},
	"Sleft":{
		"list":{
			"1001":{
				"name":"水果",
				"url":"#"
			},
			"1002":{
				"name":"跑步机",
				"url":"#"
			},
			"1003":{
				"name":"按摩器材",
				"url":"#"
			},
			"1004":{
				"name":"健身器",
				"url":"#"
			},
			"1005":{
				"name":"保健品",
				"url":"#"
			},
			"1006":{
				"name":"干果/零食",
				"url":"#"
			},
			"1007":{
				"name":"酒水",
				"url":"#"
			},
			"1008":{
				"name":"水果",
				"url":"#"
			},
			"1009":{
				"name":"大闸蟹",
				"url":"#"
			}
		},
		"pic1":{
			"1001":{
				"_img":"../images/57a82d25bb12d.jpg",
				"url":"#"
			}
		},
		"pic2":{
			"1001":{
				"_img":"../images/57baafcd7bc44.jpg",
				"url":"#"
			}
		}	
	},
	"Sright":{
		"4001":{
			"_img":"../images/5770a07b5c9fe.jpg",
			"url":"#",
			"desc":"20L禧又多土榨纯香菜籽油超值秒杀组",
			"money":"￥168",
			"buy":"购买"
		},
		"4002":{
			"_img":"../images/5757a1c1b1fbf.jpg",
			"url":"#",
			"desc":"民生益谷灵牌骨密度养护套组",
			"money":"￥299",
			"buy":"购买"
		},
		"4003":{
			"_img":"../images/57a1afc3592b5.jpg",
			"url":"#",
			"desc":"（海）柏乐园景点成人门票",
			"money":"￥169",
			"buy":"购买"
		},
		"4004":{
			"_img":"../images/569cbbb3a1d0a.jpg",
			"url":"#",
			"desc":"嘉丽购迎春白酒惊爆组",
			"money":"￥298",
			"buy":"购买"
		},
		"4005":{
			"_img":"../images/1470296666912645187.jpg",
			"url":"#",
			"desc":"（海）吴三公鸡腿菇58g*6袋+吴三公银耳28g*2袋",
			"money":"￥168",
			"buy":"购买"
		},
		"4006":{
			"_img":"../images/14643420071114444890.jpg",
			"url":"#",
			"desc":"慈生堂欧盟标准零添加纯蜂蜜",
			"money":"￥168",
			"buy":"购买"
		}
	},
	"Fleft":{
		"list":{
			"1001":{
				"name":"床品件套",
				"url":"#"
			},
			"1002":{
				"name":"凉席",
				"url":"#"
			},
			"1003":{
				"name":"清洁用品",
				"url":"#"
			},
			"1004":{
				"name":"锅具",
				"url":"#"
			},
			"1005":{
				"name":"刀具",
				"url":"#"
			},
			"1006":{
				"name":"空调扇",
				"url":"#"
			},
			"1007":{
				"name":"料理/榨汁",
				"url":"#"
			},
			"1008":{
				"name":"电饭煲",
				"url":"#"
			},
			"1009":{
				"name":"电热锅",
				"url":"#"
			}
		},
		"pic1":{
			"1001":{
				"_img":"../images/57bab13e4791f.jpg",
				"url":"#"
			}
		},
		"pic2":{
			"1001":{
				"_img":"../images/57b132b13bfdc.jpg",
				"url":"#"
			}
		}	
	},
	"Fright":{
		"5001":{
			"_img":"../images/14679608771500773372.jpg",
			"url":"#",
			"desc":"诗蘭庭寝具4+4+4特惠组",
			"money":"￥168",
			"buy":"购买"
		},
		"5002":{
			"_img":"../images/14582713371579336213.jpg",
			"url":"#",
			"desc":"德国ALES精品不锈钢实用锅具组",
			"money":"￥299",
			"buy":"购买",
		},
		"5003":{
			"_img":"../images/s1_32568.jpg",
			"url":"#",
			"desc":"小熊电脑版智能豆芽机套组",
			"money":"￥169",
			"buy":"购买",
			"key":"5003"
		},
		"5004":{
			"_img":"../images/5728647c0d6ff.jpg",
			"url":"#",
			"desc":"宝家洁自动拧水魔术平板拖超值组",
			"money":"￥298",
			"buy":"购买",
			"key":"5004"
		},
		"5005":{
			"_img":"../images/14696074251622901200.jpg",
			"url":"#",
			"desc":"达米尼BCD-515WKSD时尚银风冷无霜冰箱",
			"money":"￥168",
			"buy":"购买",
			"key":"5005"
		},
		"5006":{
			"_img":"../images/s1_32924.jpg",
			"url":"#",
			"desc":"(购销)韩妙神奇水管1+1组",
			"money":"￥168",
			"buy":"购买",
			"key":"5006"
		}
	}
}